dockerfile_generator_lrnd/__init__.py
dockerfile_generator_lrnd/base.py
dockerfile_generator_lrnd/cli.py
dockerfile_generator_lrnd/exceptions.py
dockerfile_generator_lrnd/nodejs.py
dockerfile_generator_lrnd/php.py
dockerfile_generator_lrnd/python.py
dockerfile_generator_lrnd/static.py
dockerfile_generator_lrnd/utils.py
dockerfile_generator_lrnd-0.1.4.dist-info/LICENSE
dockerfile_generator_lrnd-0.1.4.dist-info/METADATA
dockerfile_generator_lrnd-0.1.4.dist-info/WHEEL
dockerfile_generator_lrnd-0.1.4.dist-info/entry_points.txt
dockerfile_generator_lrnd-0.1.4.dist-info/RECORD
