Metadata-Version: 2.3
Name: dockerfile-generator-lrnd
Version: 0.1.4
Summary: Automatic Dockerfile generator for multiple technologies
License: MIT
Keywords: docker,dockerfile,automation,devops
Author: lrndwy
Requires-Python: >=3.12,<4.0
Classifier: License :: OSI Approved :: MIT License
Classifier: Programming Language :: Python :: 3
Classifier: Programming Language :: Python :: 3.12
Classifier: Programming Language :: Python :: 3.13
Requires-Dist: click (>=8.1.8,<9.0.0)
